netinv/__init__.py
netinv-0.1.0.dist-info/LICENSE
netinv-0.1.0.dist-info/WHEEL
netinv-0.1.0.dist-info/METADATA
netinv-0.1.0.dist-info/RECORD
